{
	"info": {
		"_postman_id": "818a604f-70c1-4c5b-96ae-2a7d29e8d593",
		"name": "Fastify",
		"schema": "https://schema.getpostman.com/json/collection/v2.1.0/collection.json"
	},
	"item": [
		{
			"name": "products",
			"request": {
				"method": "GET",
				"header": [],
				"url": {
					"raw": "http://localhost:3000/products",
					"protocol": "http",
					"host": [
						"localhost"
					],
					"port": "3000",
					"path": [
						"products"
					]
				}
			},
			"response": []
		},
		{
			"name": "products/:id",
			"request": {
				"method": "GET",
				"header": [],
				"url": {
					"raw": "http://localhost:3000/products/649d2177f598ad930a14b6b5",
					"protocol": "http",
					"host": [
						"localhost"
					],
					"port": "3000",
					"path": [
						"products",
						"649d2177f598ad930a14b6b5"
					]
				}
			},
			"response": []
		},
		{
			"name": "products/:id",
			"request": {
				"method": "DELETE",
				"header": [],
				"url": {
					"raw": "http://localhost:3000/products/649d1f334bec8ad7d086c84c",
					"protocol": "http",
					"host": [
						"localhost"
					],
					"port": "3000",
					"path": [
						"products",
						"649d1f334bec8ad7d086c84c"
					]
				}
			},
			"response": []
		},
		{
			"name": "products",
			"request": {
				"method": "POST",
				"header": [],
				"body": {
					"mode": "raw",
					"raw": "{\r\n    \"title\": \"title\",\r\n    \"price\": 100,\r\n    \"image\": \"image.url\",\r\n    \"description\": \"description\",\r\n    \"quantity\": 20\r\n}",
					"options": {
						"raw": {
							"language": "json"
						}
					}
				},
				"url": {
					"raw": "http://localhost:3000/products",
					"protocol": "http",
					"host": [
						"localhost"
					],
					"port": "3000",
					"path": [
						"products"
					]
				}
			},
			"response": []
		},
		{
			"name": "products/:id",
			"request": {
				"method": "PUT",
				"header": [],
				"body": {
					"mode": "raw",
					"raw": "{\r\n    \"image\": \"image.url\"\r\n}",
					"options": {
						"raw": {
							"language": "json"
						}
					}
				},
				"url": {
					"raw": "http://localhost:3000/products/649d2177f598ad930a14b6b5",
					"protocol": "http",
					"host": [
						"localhost"
					],
					"port": "3000",
					"path": [
						"products",
						"649d2177f598ad930a14b6b5"
					]
				}
			},
			"response": []
		}
	]
}